{
  "id": "spec-gen-sz412jzx",
  "name": "Generate New Warehouses Messages from WordPress to Telegram",
  "slug": "generate-new-warehouses-messages-from-wordpress-to-telegram",
  "description": "In Warehouses, Teams lack visibility into critical updates. Focusing on messages helps.",
  "shortDescription": "Prebuilt FlowMatch AI Original workflow using Wordpress and Telegram.",
  "originalWorkflowJson": {
    "name": "Generate New Warehouses Messages from WordPress to Telegram",
    "nodes": [
      {
        "id": "generatenewwarehousesmessagesfromwordpresstotelegramtrig",
        "name": "Schedule Cron Trigger",
        "type": "n8n-nodes-base.cron",
        "typeVersion": 1,
        "position": [
          100,
          250
        ],
        "parameters": {}
      },
      {
        "id": "generatenewwarehousesmessagesfromwordpresstotelegramnode0",
        "name": "Save to WordPress",
        "type": "n8n-nodes-base.wordpress",
        "typeVersion": 1,
        "position": [
          350,
          250
        ],
        "parameters": {}
      },
      {
        "id": "generatenewwarehousesmessagesfromwordpresstotelegramnode1",
        "name": "Save to Telegram",
        "type": "n8n-nodes-base.telegram",
        "typeVersion": 1,
        "position": [
          600,
          250
        ],
        "parameters": {}
      }
    ],
    "connections": {
      "Schedule Cron Trigger": {
        "main": [
          [
            {
              "node": "Save to WordPress",
              "index": 0
            }
          ]
        ]
      },
      "Save to WordPress": {
        "main": [
          [
            {
              "node": "Save to Telegram",
              "index": 0
            }
          ]
        ]
      }
    },
    "settings": {
      "executionTimeout": 300
    }
  },
  "normalizedWorkflowJson": {
    "connections": {
      "Save to WordPress": {
        "main": [
          [
            {
              "index": 0,
              "node": "Save to Telegram"
            }
          ]
        ]
      },
      "Schedule Cron Trigger": {
        "main": [
          [
            {
              "index": 0,
              "node": "Save to WordPress"
            }
          ]
        ]
      }
    },
    "name": "Generate New Warehouses Messages from WordPress to Telegram",
    "nodes": [
      {
        "name": "Save to Telegram",
        "parameters": {},
        "type": "n8n-nodes-base.telegram",
        "typeVersion": 1
      },
      {
        "name": "Save to WordPress",
        "parameters": {},
        "type": "n8n-nodes-base.wordpress",
        "typeVersion": 1
      },
      {
        "name": "Schedule Cron Trigger",
        "parameters": {},
        "type": "n8n-nodes-base.cron",
        "typeVersion": 1
      }
    ]
  },
  "nodeCount": 3,
  "integrationCount": 2,
  "difficulty": "Beginner",
  "estimatedSetupTime": "5 Mins",
  "integrations": [
    "Wordpress",
    "Telegram"
  ],
  "securityStatus": "Passed",
  "verified": true,
  "featured": true,
  "downloadCount": 15,
  "viewCount": 106,
  "workflowOrigin": "flowmatch_original",
  "instructionStatus": "flowmatch_original",
  "instructions": {
    "prerequisites": [
      "An active n8n instance installed locally, in a Docker container, or hosted on n8n Cloud.",
      "Basic familiarity with importing JSON templates in n8n."
    ],
    "setupInstructions": [
      "Download this FlowMatch AI original blueprint JSON file.",
      "Open your n8n workspace dashboard and import the blueprint file directly onto the node canvas.",
      "Ensure you set up credentials for all connected integrations.",
      "Test your trigger and run execution."
    ],
    "requiredAccounts": [
      "Wordpress Account",
      "Telegram Account"
    ],
    "requiredCredentials": [
      "No custom credentials required for utility-only operations."
    ],
    "configurationSteps": [
      "Locate and open the trigger node \"Scheduled\".",
      "Open the action node \"Save to WordPress\" and configure your WordPress account credentials.",
      "Open the action node \"Save to Telegram\" and configure your Telegram account credentials.",
      "Map appropriate JSON expression fields between incoming trigger payload schemas and destination nodes."
    ],
    "testingSteps": [
      "Initiate test execution using n8n's \"Test step\" mode.",
      "Execute target test scenario: Send a mock messages payload to verify end-to-end delivery.",
      "Confirm that the green execution markers light up indicating data is mapped correctly."
    ],
    "expectedResult": "New Messages are successfully processed and available in Telegram.",
    "troubleshooting": [
      "Check your credentials and API token authorizations if authorization failures block execution.",
      "Ensure expressions reference correct upstream node output keys.",
      "Review n8n execution histories logs for precise error stack traces."
    ],
    "securityNotes": [
      "Ensure that you select credentials stored in n8n's credential locker. Do not write API keys in plain text parameters.",
      "Secure webhook ingestion endpoints using headers or secret token authorizations."
    ],
    "customizationIdeas": [
      "Add Airtable for additional logging.",
      "Filter out non-new items.",
      "Add an AI translation step to qualify multilingual inputs.",
      "Add a Slack webhook node to trigger alert messages on process exceptions."
    ]
  },
  "qualityScore": 89,
  "validationStatus": "Valid",
  "provenanceStatus": "flowmatch_authored",
  "importBatch": "flowmatch-original-batch-01",
  "sources": [
    {
      "id": "src-f9jbez0e9",
      "workflowId": "spec-gen-sz412jzx",
      "sourceName": "FlowMatch AI Authoring Engine",
      "sourceAuthor": "FlowMatch AI Team",
      "sourceLicense": "MIT License",
      "sourceRepository": "https://github.com/Zie619/n8n-workflows",
      "discoveredAt": "2026-07-15T12:18:28.520Z"
    }
  ],
  "createdAt": "2026-07-15T12:18:28.520Z",
  "updatedAt": "2026-07-15T12:18:28.520Z",
  "seo": {
    "metaTitle": "Generate New Warehouses Messages from WordPress to Telegram n8n Workflow Template | FlowMatch AI",
    "metaDescription": "Automate Generate New Warehouses Messages from WordPress to Telegram with n8n. Find prebuilt setups using Wordpress, Telegram. Scanned safe, quality verified blueprint.",
    "canonicalSlug": "/workflow/generate-new-warehouses-messages-from-wordpress-to-telegram",
    "searchIntent": "Find prebuilt n8n automation blueprints for Wordpress and Telegram.",
    "primaryKeyword": "Generate New Warehouses Messages from WordPress to Telegram n8n workflow",
    "secondaryKeywords": [
      "n8n workflow template",
      "n8n automation template",
      "wordpress n8n integration",
      "telegram n8n integration",
      "beginner"
    ]
  }
}