{
  "id": "telegramtrigger-workflow-urmuz",
  "name": "Telegramtrigger Workflow",
  "slug": "telegramtrigger-workflow-4g30",
  "description": "Automated workflow: Telegramtrigger Workflow. This workflow integrates 9 different services: telegramTrigger, stickyNote, telegram, switch, set. It contains 37 nodes and follows best practices for error handling and security.",
  "shortDescription": "Telegramtrigger Workflow workflow containing 30 nodes.",
  "originalWorkflowJson": {
    "meta": {
      "instanceId": "workflow-821fcbc4",
      "versionId": "1.0.0",
      "createdAt": "2025-09-29T07:07:44.531845",
      "updatedAt": "2025-09-29T07:07:44.531984",
      "owner": "n8n-user",
      "license": "MIT",
      "category": "automation",
      "status": "active",
      "priority": "high",
      "environment": "production"
    },
    "nodes": [
      {
        "id": "5d9cf2ce-4808-4d44-9f0d-2c15d8dcea91",
        "name": "Trigger",
        "type": "n8n-nodes-base.telegramTrigger",
        "position": [
          -400,
          340
        ],
        "webhookId": "96a20e88-ba8f-4827-b874-b0a9867c59e9",
        "parameters": {
          "updates": [
            "*"
          ],
          "additionalFields": {}
        },
        "credentials": {
          "telegramApi": {
            "id": "BsrAeDsPMOnQOFa7",
            "name": "n8n template"
          }
        },
        "typeVersion": 1.1,
        "notes": "This telegramTrigger node performs automated tasks as part of the workflow."
      },
      {
        "id": "22fc0669-96f2-4767-9bc2-03644c7ced21",
        "name": "Global data",
        "type": "n8n-nodes-base.set",
        "position": [
          -200,
          340
        ],
        "parameters": {
          "options": {}
        },
        "typeVersion": 3.4,
        "notes": "This set node performs automated tasks as part of the workflow."
      },
      {
        "id": "d5925fd8-abde-45bf-ac3d-22649ecb1f4e",
        "name": "Telegram1",
        "type": "n8n-nodes-base.telegram",
        "position": [
          1700,
          -360
        ],
        "parameters": {
          "text": "Photo",
          "chatId": "={{ $('Trigger').item.json.message.from.id }}",
          "additionalFields": {
            "appendAttribution": false
          }
        },
        "credentials": {
          "telegramApi": {
            "id": "BsrAeDsPMOnQOFa7",
            "name": "n8n template"
          }
        },
        "typeVersion": 1.2,
        "notes": "This telegram node performs automated tasks as part of the workflow."
      },
      {
        "id": "5dc06f04-26b4-45af-99d6-a06b7c1b936d",
        "name": "Telegram2",
        "type": "n8n-nodes-base.telegram",
        "position": [
          1700,
          -120
        ],
        "parameters": {
          "text": "File",
          "chatId": "={{ $('Trigger').item.json.message.from.id }}",
          "additionalFields": {
            "appendAttribution": false
          }
        },
        "credentials": {
          "telegramApi": {
            "id": "BsrAeDsPMOnQOFa7",
            "name": "n8n template"
          }
        },
        "typeVersion": 1.2,
        "notes": "This telegram node performs automated tasks as part of the workflow."
      },
      {
        "id": "d036c602-17bb-45b5-b7b0-331339570cb3",
        "name": "Telegram3",
        "type": "n8n-nodes-base.telegram",
        "position": [
          1260,
          460
        ],
        "parameters": {
          "text": "Callback",
          "chatId": "={{ $('Trigger').item.json.callback_query.data }}",
          "additionalFields": {
            "appendAttribution": false
          }
        },
        "credentials": {
          "telegramApi": {
            "id": "BsrAeDsPMOnQOFa7",
            "name": "n8n template"
          }
        },
        "typeVersion": 1.2,
        "notes": "This telegram node performs automated tasks as part of the workflow."
      },
      {
        "id": "a86fe429-65df-471b-bdcb-e4765b14f109",
        "name": "Telegram4",
        "type": "n8n-nodes-base.telegram",
        "position": [
          1600,
          -700
        ],
        "parameters": {
          "text": "Text",
          "chatId": "={{ $('Trigger').item.json.message.from.id }}",
          "additionalFields": {
            "appendAttribution": false
          }
        },
        "credentials": {
          "telegramApi": {
            "id": "BsrAeDsPMOnQOFa7",
            "name": "n8n template"
          }
        },
        "typeVersion": 1.2,
        "notes": "This telegram node performs automated tasks as part of the workflow."
      },
      {
        "id": "b28ef71b-4e4b-48cb-b64d-029feee13ee4",
        "name": "Sticky Note",
        "type": "n8n-nodes-base.stickyNote",
        "position": [
          980,
          360
        ],
        "parameters": {
          "color": 7,
          "width": 1200.5980355767667,
          "height": 326.00218267794156,
          "content": "## Callback"
        },
        "typeVersion": 1,
        "notes": "This stickyNote node performs automated tasks as part of the workflow."
      },
      {
        "id": "d51d4ac4-e182-4245-b26f-248f99235de8",
        "name": "Sticky Note1",
        "type": "n8n-nodes-base.stickyNote",
        "position": [
          980,
          -920
        ],
        "parameters": {
          "color": 7,
          "width": 1200.5980355767667,
          "height": 481.314448671577,
          "content": "## Text\n"
        },
        "typeVersion": 1,
        "notes": "This stickyNote node performs automated tasks as part of the workflow."
      },
      {
        "id": "05754c06-8f64-44c6-be55-3eb480e0cb3d",
        "name": "Sticky Note2",
        "type": "n8n-nodes-base.stickyNote",
        "position": [
          980,
          -400
        ],
        "parameters": {
          "color": 7,
          "width": 1200.5980355767667,
          "height": 198.69915410333263,
          "content": "## Photo"
        },
        "typeVersion": 1,
        "notes": "This stickyNote node performs automated tasks as part of the workflow."
      },
      {
        "id": "d9906042-25cd-4812-bbf1-4c46aa2c0492",
        "name": "Sticky Note3",
        "type": "n8n-nodes-base.stickyNote",
        "position": [
          980,
          -160
        ],
        "parameters": {
          "color": 7,
          "width": 1200.5980355767667,
          "height": 198.69915410333263,
          "content": "## File"
        },
        "typeVersion": 1,
        "notes": "This stickyNote node performs automated tasks as part of the workflow."
      },
      {
        "id": "0e0bfc7f-23a3-478e-a3a1-cffbc9f9f95e",
        "name": "Sticky Note4",
        "type": "n8n-nodes-base.stickyNote",
        "position": [
          980,
          100
        ],
        "parameters": {
          "color": 7,
          "width": 1200.5980355767667,
          "height": 198.69915410333263,
          "content": "## Voice"
        },
        "typeVersion": 1,
        "notes": "This stickyNote node performs automated tasks as part of the workflow."
      },
      {
        "id": "a4519088-76c3-427c-95b6-7982814bf8e3",
        "name": "Telegram5",
        "type": "n8n-nodes-base.telegram",
        "position": [
          1700,
          140
        ],
        "parameters": {
          "text": "Voice",
          "chatId": "={{ $('Trigger').item.json.message.from.id }}",
          "additionalFields": {
            "appendAttribution": false
          }
        },
        "credentials": {
          "telegramApi": {
            "id": "BsrAeDsPMOnQOFa7",
            "name": "n8n template"
          }
        },
        "typeVersion": 1.2,
        "notes": "This telegram node performs automated tasks as part of the workflow."
      },
      {
        "id": "0b597db9-d240-4be3-90f3-095117b1c6bc",
        "name": "Switch_MessageType",
        "type": "n8n-nodes-base.switch",
        "position": [
          720,
          -120
        ],
        "parameters": {
          "rules": {
            "values": [
              {
                "outputKey": "YOUR_CREDENTIAL_HERE",
                "conditions": {
                  "options": {
                    "leftValue": "",
                    "caseSensitive": true,
                    "typeValidation": "strict"
                  },
                  "combinator": "and",
                  "conditions": [
                    {
                      "id": "360a2e5b-8736-488c-87dc-b5fcbd2b5102",
                      "operator": {
                        "type": "boolean",
                        "operation": "true",
                        "singleValue": true
                      },
                      "leftValue": "={{ $('Trigger').item.json.message.hasOwnProperty('text') }}",
                      "rightValue": "/"
                    }
                  ]
                },
                "renameOutput": true
              },
              {
                "outputKey": "YOUR_CREDENTIAL_HERE",
                "conditions": {
                  "options": {
                    "leftValue": "",
                    "caseSensitive": true,
                    "typeValidation": "strict"
                  },
                  "combinator": "and",
                  "conditions": [
                    {
                      "operator": {
                        "type": "boolean",
                        "operation": "true",
                        "singleValue": true
                      },
                      "leftValue": "={{ $('Trigger').item.json.message.hasOwnProperty('photo') }}",
                      "rightValue": ""
                    }
                  ]
                },
                "renameOutput": true
              },
              {
                "outputKey": "YOUR_CREDENTIAL_HERE",
                "conditions": {
                  "options": {
                    "leftValue": "",
                    "caseSensitive": true,
                    "typeValidation": "strict"
                  },
                  "combinator": "and",
                  "conditions": [
                    {
                      "id": "eb5a5507-4374-46c9-b8eb-25b36cbe17ee",
                      "operator": {
                        "type": "boolean",
                        "operation": "true",
                        "singleValue": true
                      },
                      "leftValue": "={{ $('Trigger').item.json.message.hasOwnProperty('document') }}",
                      "rightValue": "2"
                    }
                  ]
                },
                "renameOutput": true
              },
              {
                "outputKey": "YOUR_CREDENTIAL_HERE",
                "conditions": {
                  "options": {
                    "leftValue": "",
                    "caseSensitive": true,
                    "typeValidation": "strict"
                  },
                  "combinator": "and",
                  "conditions": [
                    {
                      "id": "b5a43050-e657-4b56-aa9b-290a94aa8902",
                      "operator": {
                        "type": "boolean",
                        "operation": "true",
                        "singleValue": true
                      },
                      "leftValue": "={{ $('Trigger').item.json.message.hasOwnProperty('voice') }}",
                      "rightValue": ""
                    }
                  ]
                },
                "renameOutput": true
              }
            ]
          },
          "options": {}
        },
        "typeVersion": 3,
        "notes": "This switch node performs automated tasks as part of the workflow."
      },
      {
        "id": "efb08696-e76f-494c-8872-d117a379adec",
        "name": "Sticky Note5",
        "type": "n8n-nodes-base.stickyNote",
        "position": [
          980,
          -1440
        ],
        "parameters": {
          "color": 7,
          "width": 1195.9520561291508,
          "height": 481.314448671577,
          "content": "## Commands"
        },
        "typeVersion": 1,
        "notes": "This stickyNote node performs automated tasks as part of the workflow."
      },
      {
        "id": "7edecce3-6371-45ab-8dc1-f3e1a2052daa",
        "name": "Telegram6",
        "type": "n8n-nodes-base.telegram",
        "position": [
          1840,
          -1180
        ],
        "parameters": {
          "text": "Don't know the command",
          "chatId": "={{ $('Trigger').item.json.message.from.id }}",
          "additionalFields": {
            "appendAttribution": false
          }
        },
        "credentials": {
          "telegramApi": {
            "id": "BsrAeDsPMOnQOFa7",
            "name": "n8n template"
          }
        },
        "typeVersion": 1.2,
        "notes": "This telegram node performs automated tasks as part of the workflow."
      },
      {
        "id": "c3b030e2-a085-4e21-8645-0224d6bb7c35",
        "name": "Menu",
        "type": "n8n-nodes-base.switch",
        "position": [
          1420,
          460
        ],
        "parameters": {
          "rules": {
            "values": [
              {
                "outputKey": "YOUR_CREDENTIAL_HERE",
                "conditions": {
                  "options": {
                    "leftValue": "",
                    "caseSensitive": true,
                    "typeValidation": "strict"
                  },
                  "combinator": "and",
                  "conditions": [
                    {
                      "id": "798e1a40-e85b-4294-afcb-b129f92eb833",
                      "operator": {
                        "name": "filter.operator.equals",
                        "type": "string",
                        "operation": "equals"
                      },
                      "leftValue": "={{ $('Trigger').item.json.callback_query.data }}",
                      "rightValue": "menu_conditions"
                    }
                  ]
                },
                "renameOutput": true
              },
              {
                "outputKey": "YOUR_CREDENTIAL_HERE",
                "conditions": {
                  "options": {
                    "leftValue": "",
                    "caseSensitive": true,
                    "typeValidation": "strict"
                  },
                  "combinator": "and",
                  "conditions": [
                    {
                      "id": "f91b8a94-8961-4d20-ae9c-0ee34ff04000",
                      "operator": {
                        "name": "filter.operator.equals",
                        "type": "string",
                        "operation": "equals"
                      },
                      "leftValue": "={{ $('Trigger').item.json.callback_query.data }}",
                      "rightValue": "menu_reviews"
                    }
                  ]
                },
                "renameOutput": true
              }
            ]
          },
          "options": {}
        },
        "typeVersion": 3,
        "notes": "This switch node performs automated tasks as part of the workflow."
      },
      {
        "id": "71907904-21f3-459c-a445-ca44a432dd36",
        "name": "Command?",
        "type": "n8n-nodes-base.if",
        "position": [
          1380,
          -760
        ],
        "parameters": {
          "options": {},
          "conditions": {
            "options": {
              "leftValue": "",
              "caseSensitive": true,
              "typeValidation": "strict"
            },
            "combinator": "and",
            "conditions": [
              {
                "id": "a2025331-2c2b-4df8-9e23-37035a5c808a",
                "operator": {
                  "type": "string",
                  "operation": "startsWith"
                },
                "leftValue": "={{ $('Trigger').item.json.message.text }}\n",
                "rightValue": "/"
              }
            ]
          }
        },
        "typeVersion": 2,
        "notes": "This if node performs automated tasks as part of the workflow."
      },
      {
        "id": "23e5c351-095b-4485-ad09-4dc4df195a8d",
        "name": "Change status",
        "type": "n8n-nodes-base.googleSheets",
        "position": [
          1460,
          1220
        ],
        "parameters": {
          "columns": {
            "value": {
              "Status": "0"
            },
            "schema": [
              {
                "id": "ID",
                "type": "string",
                "display": true,
                "removed": false,
                "required": false,
                "displayName": "ID",
                "defaultMatch": false,
                "canBeUsedToMatch": true
              },
              {
                "id": "Name",
                "type": "string",
                "display": true,
                "removed": true,
                "required": false,
                "displayName": "Name",
                "defaultMatch": false,
                "canBeUsedToMatch": true
              },
              {
                "id": "Lastname",
                "type": "string",
                "display": true,
                "removed": true,
                "required": false,
                "displayName": "Lastname",
                "defaultMatch": false,
                "canBeUsedToMatch": true
              },
              {
                "id": "Username",
                "type": "string",
                "display": true,
                "removed": true,
                "required": false,
                "displayName": "Username",
                "defaultMatch": false,
                "canBeUsedToMatch": true
              },
              {
                "id": "Date",
                "type": "string",
                "display": true,
                "removed": true,
                "required": false,
                "displayName": "Date",
                "defaultMatch": false,
                "canBeUsedToMatch": true
              },
              {
                "id": "Language",
                "type": "string",
                "display": true,
                "removed": true,
                "required": false,
                "displayName": "Language",
                "defaultMatch": false,
                "canBeUsedToMatch": true
              },
              {
                "id": "Status",
                "type": "string",
                "display": true,
                "required": false,
                "displayName": "Status",
                "defaultMatch": false,
                "canBeUsedToMatch": true
              },
              {
                "id": "Balance",
                "type": "string",
                "display": true,
                "removed": true,
                "required": false,
                "displayName": "Balance",
                "defaultMatch": false,
                "canBeUsedToMatch": true
              },
              {
                "id": "row_number",
                "type": "string",
                "display": true,
                "removed": true,
                "readOnly": true,
                "required": false,
                "displayName": "row_number",
                "defaultMatch": false,
                "canBeUsedToMatch": true
              }
            ],
            "mappingMode": "defineBelow",
            "matchingColumns": [
              "ID"
            ]
          },
          "options": {},
          "operation": "update",
          "sheetName": {
            "__rl": true,
            "mode": "list",
            "value": "gid=0",
            "cachedResultUrl": "{{ $env.WEBHOOK_URL }}",
            "cachedResultName": "USERS"
          },
          "documentId": {
            "__rl": true,
            "mode": "url",
            "value": "{{ $env.WEBHOOK_URL }}"
          }
        },
        "credentials": {
          "googleSheetsOAuth2Api": {
            "id": "{{ $credentials.googleSheetsOAuth2Api.id }}",
            "name": "Google Sheets account"
          }
        },
        "typeVersion": 4.4,
        "notes": "This googleSheets node performs automated tasks as part of the workflow."
      },
      {
        "id": "12e9c69a-ac4d-4c1b-ba2e-18602a1ac715",
        "name": "Start bot?",
        "type": "n8n-nodes-base.if",
        "position": [
          1260,
          1040
        ],
        "parameters": {
          "options": {},
          "conditions": {
            "options": {
              "leftValue": "",
              "caseSensitive": true,
              "typeValidation": "strict"
            },
            "combinator": "and",
            "conditions": [
              {
                "id": "253b4dfb-2b86-499a-a1a6-b6d916c9c25f",
                "operator": {
                  "name": "filter.operator.equals",
                  "type": "string",
                  "operation": "equals"
                },
                "leftValue": "={{ $('Trigger').item.json.my_chat_member.new_chat_member.status }}",
                "rightValue": "member"
              }
            ]
          }
        },
        "typeVersion": 2.1,
        "notes": "This if node performs automated tasks as part of the workflow."
      },
      {
        "id": "b60a7063-a62f-4fbe-bc33-40ff55170f3e",
        "name": "Register",
        "type": "n8n-nodes-base.executeWorkflow",
        "position": [
          1620,
          920
        ],
        "parameters": {
          "options": {
            "waitForSubWorkflow": false
          },
          "workflowId": "XZKoHGcXJE1fUizb"
        },
        "typeVersion": 1,
        "notes": "This executeWorkflow node performs automated tasks as part of the workflow."
      },
      {
        "id": "6a7249dd-f664-4115-a907-883d1da4e1c5",
        "name": "Payment Handler",
        "type": "n8n-nodes-base.executeWorkflow",
        "position": [
          1460,
          1660
        ],
        "parameters": {
          "options": {},
          "workflowId": {
            "__rl": true,
            "mode": "id",
            "value": "lPX901W8CIMbKbww"
          }
        },
        "typeVersion": 1.1,
        "notes": "This executeWorkflow node performs automated tasks as part of the workflow."
      },
      {
        "id": "586f875f-e119-467e-8a3d-6090b8eaed80",
        "name": "Trigger Data for Payment",
        "type": "n8n-nodes-base.set",
        "notes": "Chat ID required. \n\nSend action name to handle it inside Payment workflow",
        "position": [
          1280,
          1660
        ],
        "parameters": {
          "mode": "raw",
          "options": {},
          "jsonOutput": "={{ Object.assign({}, $('Trigger').item.json, { \"action\": \"HandlePayment\" }) }}"
        },
        "notesInFlow": true,
        "typeVersion": 3.4
      },
      {
        "id": "f6f231a0-f5b7-4e58-acda-4f8dfe46a666",
        "name": "Trigger Data for Register",
        "type": "n8n-nodes-base.set",
        "position": [
          1460,
          920
        ],
        "parameters": {
          "mode": "raw",
          "options": {},
          "jsonOutput": "={{ $('Trigger').item.json }}"
        },
        "typeVersion": 3.4,
        "notes": "This set node performs automated tasks as part of the workflow."
      },
      {
        "id": "b7287bcc-b4d0-4b42-bdfc-eeb8c1a0c289",
        "name": "Switch",
        "type": "n8n-nodes-base.switch",
        "position": [
          -20,
          340
        ],
        "parameters": {
          "rules": {
            "values": [
              {
                "outputKey": "YOUR_CREDENTIAL_HERE",
                "conditions": {
                  "options": {
                    "leftValue": "",
                    "caseSensitive": true,
                    "typeValidation": "strict"
                  },
                  "combinator": "and",
                  "conditions": [
                    {
                      "id": "360a2e5b-8736-488c-87dc-b5fcbd2b5102",
                      "operator": {
                        "type": "boolean",
                        "operation": "true",
                        "singleValue": true
                      },
                      "leftValue": "={{ $('Trigger').item.json.message && (!$('Trigger').item.json.message.successful_payment) }}",
                      "rightValue": "/"
                    }
                  ]
                },
                "renameOutput": true
              },
              {
                "outputKey": "YOUR_CREDENTIAL_HERE",
                "conditions": {
                  "options": {
                    "leftValue": "",
                    "caseSensitive": true,
                    "typeValidation": "strict"
                  },
                  "combinator": "and",
                  "conditions": [
                    {
                      "operator": {
                        "type": "boolean",
                        "operation": "true",
                        "singleValue": true
                      },
                      "leftValue": "={{ $('Trigger').item.json.hasOwnProperty('callback_query') }}",
                      "rightValue": ""
                    }
                  ]
                },
                "renameOutput": true
              },
              {
                "outputKey": "YOUR_CREDENTIAL_HERE",
                "conditions": {
                  "options": {
                    "leftValue": "",
                    "caseSensitive": true,
                    "typeValidation": "strict"
                  },
                  "combinator": "and",
                  "conditions": [
                    {
                      "id": "e014a230-519a-4028-98b3-33c10d408c85",
                      "operator": {
                        "type": "boolean",
                        "operation": "true",
                        "singleValue": true
                      },
                      "leftValue": "={{ $('Trigger').item.json.hasOwnProperty('my_chat_member') }}",
                      "rightValue": "System"
                    }
                  ]
                },
                "renameOutput": true
              },
              {
                "outputKey": "YOUR_CREDENTIAL_HERE",
                "conditions": {
                  "options": {
                    "leftValue": "",
                    "caseSensitive": true,
                    "typeValidation": "strict"
                  },
                  "combinator": "and",
                  "conditions": [
                    {
                      "id": "b03aaa37-d57f-437c-acb2-de2068d3241a",
                      "operator": {
                        "type": "boolean",
                        "operation": "true",
                        "singleValue": true
                      },
                      "leftValue": "={{ $('Trigger').item.json.hasOwnProperty('pre_checkout_query') || $('Trigger').item.json.message.hasOwnProperty('successful_payment') }}",
                      "rightValue": ""
                    }
                  ]
                },
                "renameOutput": true
              }
            ]
          },
          "options": {}
        },
        "typeVersion": 3,
        "notes": "This switch node performs automated tasks as part of the workflow."
      },
      {
        "id": "509c5575-2226-486c-8398-887eb69a74f8",
        "name": "Data for Invoice",
        "type": "n8n-nodes-base.set",
        "notes": "Chat ID required. \n\nSend action name to handle it inside Payment workflow",
        "position": [
          1840,
          -1380
        ],
        "parameters": {
          "mode": "raw",
          "options": {},
          "jsonOutput": "={{ Object.assign({}, $('Trigger').item.json, { \"action\": \"SendInvoice\" }) }}"
        },
        "notesInFlow": true,
        "typeVersion": 3.4
      },
      {
        "id": "6634d3a8-848a-4a14-ba37-58f33e3409f2",
        "name": "Send Invoice",
        "type": "n8n-nodes-base.executeWorkflow",
        "position": [
          2040,
          -1380
        ],
        "parameters": {
          "options": {
            "waitForSubWorkflow": false
          },
          "workflowId": "lPX901W8CIMbKbww"
        },
        "typeVersion": 1,
        "notes": "This executeWorkflow node performs automated tasks as part of the workflow."
      },
      {
        "id": "e4bef639-3451-4ddc-ad26-481ba2acf33d",
        "name": "Sticky Note6",
        "type": "n8n-nodes-base.stickyNote",
        "position": [
          980,
          820
        ],
        "parameters": {
          "color": 7,
          "width": 1216.6513404859077,
          "height": 612.9550079288388,
          "content": "## New member or Member left"
        },
        "typeVersion": 1,
        "notes": "This stickyNote node performs automated tasks as part of the workflow."
      },
      {
        "id": "4affaf7d-0694-4aa0-9616-8e12ca5bee15",
        "name": "Sticky Note7",
        "type": "n8n-nodes-base.stickyNote",
        "position": [
          980,
          1500
        ],
        "parameters": {
          "color": 7,
          "width": 1216.6513404859077,
          "height": 496.56854733756575,
          "content": "## Payment handler"
        },
        "typeVersion": 1,
        "notes": "This stickyNote node performs automated tasks as part of the workflow."
      },
      {
        "id": "58008f10-7336-4633-ab15-51556e3b53bd",
        "name": "Switch_Commands",
        "type": "n8n-nodes-base.switch",
        "position": [
          1540,
          -1280
        ],
        "parameters": {
          "rules": {
            "values": [
              {
                "outputKey": "YOUR_CREDENTIAL_HERE",
                "conditions": {
                  "options": {
                    "leftValue": "",
                    "caseSensitive": true,
                    "typeValidation": "strict"
                  },
                  "combinator": "and",
                  "conditions": [
                    {
                      "id": "360a2e5b-8736-488c-87dc-b5fcbd2b5102",
                      "operator": {
                        "type": "string",
                        "operation": "contains"
                      },
                      "leftValue": "={{ $('Trigger').item.json.message.text }}",
                      "rightValue": "/pay"
                    }
                  ]
                },
                "renameOutput": true
              },
              {
                "outputKey": "YOUR_CREDENTIAL_HERE",
                "conditions": {
                  "options": {
                    "leftValue": "",
                    "caseSensitive": true,
                    "typeValidation": "strict"
                  },
                  "combinator": "and",
                  "conditions": [
                    {
                      "id": "546c81bf-2ee0-46b2-847b-1f92b84efaf3",
                      "operator": {
                        "type": "string",
                        "operation": "contains"
                      },
                      "leftValue": "={{ $('Trigger').item.json.message.text }}",
                      "rightValue": "/command2"
                    }
                  ]
                },
                "renameOutput": true
              }
            ]
          },
          "options": {
            "fallbackOutput": "extra"
          }
        },
        "typeVersion": 3,
        "notes": "This switch node performs automated tasks as part of the workflow."
      },
      {
        "id": "error-0b5d4223",
        "name": "Error Handler",
        "type": "n8n-nodes-base.stopAndError",
        "typeVersion": 1,
        "position": [
          1000,
          400
        ],
        "parameters": {
          "message": "Workflow execution error",
          "options": {}
        }
      }
    ],
    "pinData": {},
    "connections": {
      "5d9cf2ce-4808-4d44-9f0d-2c15d8dcea91": {
        "main": [
          [
            {
              "node": "error-handler-5d9cf2ce-4808-4d44-9f0d-2c15d8dcea91-77e7588b",
              "type": "main",
              "index": 0
            }
          ]
        ]
      },
      "d5925fd8-abde-45bf-ac3d-22649ecb1f4e": {
        "main": [
          [
            {
              "node": "error-handler-d5925fd8-abde-45bf-ac3d-22649ecb1f4e-e087d069",
              "type": "main",
              "index": 0
            }
          ]
        ]
      },
      "5dc06f04-26b4-45af-99d6-a06b7c1b936d": {
        "main": [
          [
            {
              "node": "error-handler-5dc06f04-26b4-45af-99d6-a06b7c1b936d-f1f31292",
              "type": "main",
              "index": 0
            }
          ]
        ]
      },
      "d036c602-17bb-45b5-b7b0-331339570cb3": {
        "main": [
          [
            {
              "node": "error-handler-d036c602-17bb-45b5-b7b0-331339570cb3-f84e363f",
              "type": "main",
              "index": 0
            }
          ]
        ]
      },
      "a86fe429-65df-471b-bdcb-e4765b14f109": {
        "main": [
          [
            {
              "node": "error-handler-a86fe429-65df-471b-bdcb-e4765b14f109-90c9c0ca",
              "type": "main",
              "index": 0
            }
          ]
        ]
      },
      "a4519088-76c3-427c-95b6-7982814bf8e3": {
        "main": [
          [
            {
              "node": "error-handler-a4519088-76c3-427c-95b6-7982814bf8e3-a5e4228d",
              "type": "main",
              "index": 0
            }
          ]
        ]
      },
      "7edecce3-6371-45ab-8dc1-f3e1a2052daa": {
        "main": [
          [
            {
              "node": "error-handler-7edecce3-6371-45ab-8dc1-f3e1a2052daa-dabbd7fa",
              "type": "main",
              "index": 0
            }
          ]
        ]
      },
      "23e5c351-095b-4485-ad09-4dc4df195a8d": {
        "main": [
          [
            {
              "node": "error-handler-23e5c351-095b-4485-ad09-4dc4df195a8d-f4599d15",
              "type": "main",
              "index": 0
            }
          ]
        ]
      }
    },
    "name": "Telegramtrigger Workflow",
    "settings": {
      "executionOrder": "v1",
      "saveManualExecutions": true,
      "callerPolicy": "workflowsFromSameOwner",
      "errorWorkflow": null,
      "timezone": "UTC",
      "executionTimeout": 3600,
      "maxExecutions": 1000,
      "retryOnFail": true,
      "retryCount": 3,
      "retryDelay": 1000
    },
    "description": "Automated workflow: Telegramtrigger Workflow. This workflow integrates 9 different services: telegramTrigger, stickyNote, telegram, switch, set. It contains 37 nodes and follows best practices for error handling and security.",
    "tags": [
      "automation",
      "n8n",
      "production-ready",
      "excellent",
      "optimized"
    ],
    "notes": "Excellent quality workflow: Telegramtrigger Workflow. This workflow has been optimized for production use with comprehensive error handling, security, and documentation."
  },
  "normalizedWorkflowJson": {
    "connections": {
      "23e5c351-095b-4485-ad09-4dc4df195a8d": {
        "main": [
          [
            {
              "index": 0,
              "node": "error-handler-23e5c351-095b-4485-ad09-4dc4df195a8d-f4599d15"
            }
          ]
        ]
      },
      "5d9cf2ce-4808-4d44-9f0d-2c15d8dcea91": {
        "main": [
          [
            {
              "index": 0,
              "node": "error-handler-5d9cf2ce-4808-4d44-9f0d-2c15d8dcea91-77e7588b"
            }
          ]
        ]
      },
      "5dc06f04-26b4-45af-99d6-a06b7c1b936d": {
        "main": [
          [
            {
              "index": 0,
              "node": "error-handler-5dc06f04-26b4-45af-99d6-a06b7c1b936d-f1f31292"
            }
          ]
        ]
      },
      "7edecce3-6371-45ab-8dc1-f3e1a2052daa": {
        "main": [
          [
            {
              "index": 0,
              "node": "error-handler-7edecce3-6371-45ab-8dc1-f3e1a2052daa-dabbd7fa"
            }
          ]
        ]
      },
      "a4519088-76c3-427c-95b6-7982814bf8e3": {
        "main": [
          [
            {
              "index": 0,
              "node": "error-handler-a4519088-76c3-427c-95b6-7982814bf8e3-a5e4228d"
            }
          ]
        ]
      },
      "a86fe429-65df-471b-bdcb-e4765b14f109": {
        "main": [
          [
            {
              "index": 0,
              "node": "error-handler-a86fe429-65df-471b-bdcb-e4765b14f109-90c9c0ca"
            }
          ]
        ]
      },
      "d036c602-17bb-45b5-b7b0-331339570cb3": {
        "main": [
          [
            {
              "index": 0,
              "node": "error-handler-d036c602-17bb-45b5-b7b0-331339570cb3-f84e363f"
            }
          ]
        ]
      },
      "d5925fd8-abde-45bf-ac3d-22649ecb1f4e": {
        "main": [
          [
            {
              "index": 0,
              "node": "error-handler-d5925fd8-abde-45bf-ac3d-22649ecb1f4e-e087d069"
            }
          ]
        ]
      }
    },
    "name": "Telegramtrigger Workflow",
    "nodes": [
      {
        "credentials": {
          "googleSheetsOAuth2Api": {
            "id": "REDACTED"
          }
        },
        "name": "Change status",
        "parameters": {
          "columns": {
            "mappingMode": "defineBelow",
            "matchingColumns": [
              "ID"
            ],
            "schema": [
              {
                "canBeUsedToMatch": true,
                "defaultMatch": false,
                "display": true,
                "displayName": "ID",
                "id": "ID",
                "removed": false,
                "required": false,
                "type": "string"
              },
              {
                "canBeUsedToMatch": true,
                "defaultMatch": false,
                "display": true,
                "displayName": "Name",
                "id": "Name",
                "removed": true,
                "required": false,
                "type": "string"
              },
              {
                "canBeUsedToMatch": true,
                "defaultMatch": false,
                "display": true,
                "displayName": "Lastname",
                "id": "Lastname",
                "removed": true,
                "required": false,
                "type": "string"
              },
              {
                "canBeUsedToMatch": true,
                "defaultMatch": false,
                "display": true,
                "displayName": "Username",
                "id": "Username",
                "removed": true,
                "required": false,
                "type": "string"
              },
              {
                "canBeUsedToMatch": true,
                "defaultMatch": false,
                "display": true,
                "displayName": "Date",
                "id": "Date",
                "removed": true,
                "required": false,
                "type": "string"
              },
              {
                "canBeUsedToMatch": true,
                "defaultMatch": false,
                "display": true,
                "displayName": "Language",
                "id": "Language",
                "removed": true,
                "required": false,
                "type": "string"
              },
              {
                "canBeUsedToMatch": true,
                "defaultMatch": false,
                "display": true,
                "displayName": "Status",
                "id": "Status",
                "required": false,
                "type": "string"
              },
              {
                "canBeUsedToMatch": true,
                "defaultMatch": false,
                "display": true,
                "displayName": "Balance",
                "id": "Balance",
                "removed": true,
                "required": false,
                "type": "string"
              },
              {
                "canBeUsedToMatch": true,
                "defaultMatch": false,
                "display": true,
                "displayName": "row_number",
                "id": "row_number",
                "readOnly": true,
                "removed": true,
                "required": false,
                "type": "string"
              }
            ],
            "value": {
              "Status": "0"
            }
          },
          "documentId": {
            "__rl": true,
            "mode": "url",
            "value": "{{ $env.WEBHOOK_URL }}"
          },
          "operation": "update",
          "options": {},
          "sheetName": {
            "__rl": true,
            "cachedResultName": "USERS",
            "cachedResultUrl": "{{ $env.WEBHOOK_URL }}",
            "mode": "list",
            "value": "gid=0"
          }
        },
        "type": "n8n-nodes-base.googleSheets",
        "typeVersion": 4.4
      },
      {
        "name": "Command?",
        "parameters": {
          "conditions": {
            "combinator": "and",
            "conditions": [
              {
                "id": "a2025331-2c2b-4df8-9e23-37035a5c808a",
                "leftValue": "={{ $('Trigger').item.json.message.text }}\n",
                "operator": {
                  "operation": "startsWith",
                  "type": "string"
                },
                "rightValue": "/"
              }
            ],
            "options": {
              "caseSensitive": true,
              "leftValue": "",
              "typeValidation": "strict"
            }
          },
          "options": {}
        },
        "type": "n8n-nodes-base.if",
        "typeVersion": 2
      },
      {
        "name": "Data for Invoice",
        "parameters": {
          "jsonOutput": "={{ Object.assign({}, $('Trigger').item.json, { \"action\": \"SendInvoice\" }) }}",
          "mode": "raw",
          "options": {}
        },
        "type": "n8n-nodes-base.set",
        "typeVersion": 3.4
      },
      {
        "name": "Error Handler",
        "parameters": {
          "message": "Workflow execution error",
          "options": {}
        },
        "type": "n8n-nodes-base.stopAndError",
        "typeVersion": 1
      },
      {
        "name": "Global data",
        "parameters": {
          "options": {}
        },
        "type": "n8n-nodes-base.set",
        "typeVersion": 3.4
      },
      {
        "name": "Menu",
        "parameters": {
          "options": {},
          "rules": {
            "values": [
              {
                "conditions": {
                  "combinator": "and",
                  "conditions": [
                    {
                      "id": "798e1a40-e85b-4294-afcb-b129f92eb833",
                      "leftValue": "={{ $('Trigger').item.json.callback_query.data }}",
                      "operator": {
                        "name": "filter.operator.equals",
                        "operation": "equals",
                        "type": "string"
                      },
                      "rightValue": "menu_conditions"
                    }
                  ],
                  "options": {
                    "caseSensitive": true,
                    "leftValue": "",
                    "typeValidation": "strict"
                  }
                },
                "outputKey": "YOUR_CREDENTIAL_HERE",
                "renameOutput": true
              },
              {
                "conditions": {
                  "combinator": "and",
                  "conditions": [
                    {
                      "id": "f91b8a94-8961-4d20-ae9c-0ee34ff04000",
                      "leftValue": "={{ $('Trigger').item.json.callback_query.data }}",
                      "operator": {
                        "name": "filter.operator.equals",
                        "operation": "equals",
                        "type": "string"
                      },
                      "rightValue": "menu_reviews"
                    }
                  ],
                  "options": {
                    "caseSensitive": true,
                    "leftValue": "",
                    "typeValidation": "strict"
                  }
                },
                "outputKey": "YOUR_CREDENTIAL_HERE",
                "renameOutput": true
              }
            ]
          }
        },
        "type": "n8n-nodes-base.switch",
        "typeVersion": 3
      },
      {
        "name": "Payment Handler",
        "parameters": {
          "options": {},
          "workflowId": {
            "__rl": true,
            "mode": "id",
            "value": "lPX901W8CIMbKbww"
          }
        },
        "type": "n8n-nodes-base.executeWorkflow",
        "typeVersion": 1.1
      },
      {
        "name": "Register",
        "parameters": {
          "options": {
            "waitForSubWorkflow": false
          },
          "workflowId": "XZKoHGcXJE1fUizb"
        },
        "type": "n8n-nodes-base.executeWorkflow",
        "typeVersion": 1
      },
      {
        "name": "Send Invoice",
        "parameters": {
          "options": {
            "waitForSubWorkflow": false
          },
          "workflowId": "lPX901W8CIMbKbww"
        },
        "type": "n8n-nodes-base.executeWorkflow",
        "typeVersion": 1
      },
      {
        "name": "Start bot?",
        "parameters": {
          "conditions": {
            "combinator": "and",
            "conditions": [
              {
                "id": "253b4dfb-2b86-499a-a1a6-b6d916c9c25f",
                "leftValue": "={{ $('Trigger').item.json.my_chat_member.new_chat_member.status }}",
                "operator": {
                  "name": "filter.operator.equals",
                  "operation": "equals",
                  "type": "string"
                },
                "rightValue": "member"
              }
            ],
            "options": {
              "caseSensitive": true,
              "leftValue": "",
              "typeValidation": "strict"
            }
          },
          "options": {}
        },
        "type": "n8n-nodes-base.if",
        "typeVersion": 2.1
      },
      {
        "name": "Sticky Note",
        "parameters": {
          "color": 7,
          "content": "## Callback",
          "height": 326.00218267794156,
          "width": 1200.5980355767667
        },
        "type": "n8n-nodes-base.stickyNote",
        "typeVersion": 1
      },
      {
        "name": "Sticky Note1",
        "parameters": {
          "color": 7,
          "content": "## Text\n",
          "height": 481.314448671577,
          "width": 1200.5980355767667
        },
        "type": "n8n-nodes-base.stickyNote",
        "typeVersion": 1
      },
      {
        "name": "Sticky Note2",
        "parameters": {
          "color": 7,
          "content": "## Photo",
          "height": 198.69915410333263,
          "width": 1200.5980355767667
        },
        "type": "n8n-nodes-base.stickyNote",
        "typeVersion": 1
      },
      {
        "name": "Sticky Note3",
        "parameters": {
          "color": 7,
          "content": "## File",
          "height": 198.69915410333263,
          "width": 1200.5980355767667
        },
        "type": "n8n-nodes-base.stickyNote",
        "typeVersion": 1
      },
      {
        "name": "Sticky Note4",
        "parameters": {
          "color": 7,
          "content": "## Voice",
          "height": 198.69915410333263,
          "width": 1200.5980355767667
        },
        "type": "n8n-nodes-base.stickyNote",
        "typeVersion": 1
      },
      {
        "name": "Sticky Note5",
        "parameters": {
          "color": 7,
          "content": "## Commands",
          "height": 481.314448671577,
          "width": 1195.9520561291508
        },
        "type": "n8n-nodes-base.stickyNote",
        "typeVersion": 1
      },
      {
        "name": "Sticky Note6",
        "parameters": {
          "color": 7,
          "content": "## New member or Member left",
          "height": 612.9550079288388,
          "width": 1216.6513404859077
        },
        "type": "n8n-nodes-base.stickyNote",
        "typeVersion": 1
      },
      {
        "name": "Sticky Note7",
        "parameters": {
          "color": 7,
          "content": "## Payment handler",
          "height": 496.56854733756575,
          "width": 1216.6513404859077
        },
        "type": "n8n-nodes-base.stickyNote",
        "typeVersion": 1
      },
      {
        "name": "Switch",
        "parameters": {
          "options": {},
          "rules": {
            "values": [
              {
                "conditions": {
                  "combinator": "and",
                  "conditions": [
                    {
                      "id": "360a2e5b-8736-488c-87dc-b5fcbd2b5102",
                      "leftValue": "={{ $('Trigger').item.json.message && (!$('Trigger').item.json.message.successful_payment) }}",
                      "operator": {
                        "operation": "true",
                        "singleValue": true,
                        "type": "boolean"
                      },
                      "rightValue": "/"
                    }
                  ],
                  "options": {
                    "caseSensitive": true,
                    "leftValue": "",
                    "typeValidation": "strict"
                  }
                },
                "outputKey": "YOUR_CREDENTIAL_HERE",
                "renameOutput": true
              },
              {
                "conditions": {
                  "combinator": "and",
                  "conditions": [
                    {
                      "leftValue": "={{ $('Trigger').item.json.hasOwnProperty('callback_query') }}",
                      "operator": {
                        "operation": "true",
                        "singleValue": true,
                        "type": "boolean"
                      },
                      "rightValue": ""
                    }
                  ],
                  "options": {
                    "caseSensitive": true,
                    "leftValue": "",
                    "typeValidation": "strict"
                  }
                },
                "outputKey": "YOUR_CREDENTIAL_HERE",
                "renameOutput": true
              },
              {
                "conditions": {
                  "combinator": "and",
                  "conditions": [
                    {
                      "id": "e014a230-519a-4028-98b3-33c10d408c85",
                      "leftValue": "={{ $('Trigger').item.json.hasOwnProperty('my_chat_member') }}",
                      "operator": {
                        "operation": "true",
                        "singleValue": true,
                        "type": "boolean"
                      },
                      "rightValue": "System"
                    }
                  ],
                  "options": {
                    "caseSensitive": true,
                    "leftValue": "",
                    "typeValidation": "strict"
                  }
                },
                "outputKey": "YOUR_CREDENTIAL_HERE",
                "renameOutput": true
              },
              {
                "conditions": {
                  "combinator": "and",
                  "conditions": [
                    {
                      "id": "b03aaa37-d57f-437c-acb2-de2068d3241a",
                      "leftValue": "={{ $('Trigger').item.json.hasOwnProperty('pre_checkout_query') || $('Trigger').item.json.message.hasOwnProperty('successful_payment') }}",
                      "operator": {
                        "operation": "true",
                        "singleValue": true,
                        "type": "boolean"
                      },
                      "rightValue": ""
                    }
                  ],
                  "options": {
                    "caseSensitive": true,
                    "leftValue": "",
                    "typeValidation": "strict"
                  }
                },
                "outputKey": "YOUR_CREDENTIAL_HERE",
                "renameOutput": true
              }
            ]
          }
        },
        "type": "n8n-nodes-base.switch",
        "typeVersion": 3
      },
      {
        "name": "Switch_Commands",
        "parameters": {
          "options": {
            "fallbackOutput": "extra"
          },
          "rules": {
            "values": [
              {
                "conditions": {
                  "combinator": "and",
                  "conditions": [
                    {
                      "id": "360a2e5b-8736-488c-87dc-b5fcbd2b5102",
                      "leftValue": "={{ $('Trigger').item.json.message.text }}",
                      "operator": {
                        "operation": "contains",
                        "type": "string"
                      },
                      "rightValue": "/pay"
                    }
                  ],
                  "options": {
                    "caseSensitive": true,
                    "leftValue": "",
                    "typeValidation": "strict"
                  }
                },
                "outputKey": "YOUR_CREDENTIAL_HERE",
                "renameOutput": true
              },
              {
                "conditions": {
                  "combinator": "and",
                  "conditions": [
                    {
                      "id": "546c81bf-2ee0-46b2-847b-1f92b84efaf3",
                      "leftValue": "={{ $('Trigger').item.json.message.text }}",
                      "operator": {
                        "operation": "contains",
                        "type": "string"
                      },
                      "rightValue": "/command2"
                    }
                  ],
                  "options": {
                    "caseSensitive": true,
                    "leftValue": "",
                    "typeValidation": "strict"
                  }
                },
                "outputKey": "YOUR_CREDENTIAL_HERE",
                "renameOutput": true
              }
            ]
          }
        },
        "type": "n8n-nodes-base.switch",
        "typeVersion": 3
      },
      {
        "name": "Switch_MessageType",
        "parameters": {
          "options": {},
          "rules": {
            "values": [
              {
                "conditions": {
                  "combinator": "and",
                  "conditions": [
                    {
                      "id": "360a2e5b-8736-488c-87dc-b5fcbd2b5102",
                      "leftValue": "={{ $('Trigger').item.json.message.hasOwnProperty('text') }}",
                      "operator": {
                        "operation": "true",
                        "singleValue": true,
                        "type": "boolean"
                      },
                      "rightValue": "/"
                    }
                  ],
                  "options": {
                    "caseSensitive": true,
                    "leftValue": "",
                    "typeValidation": "strict"
                  }
                },
                "outputKey": "YOUR_CREDENTIAL_HERE",
                "renameOutput": true
              },
              {
                "conditions": {
                  "combinator": "and",
                  "conditions": [
                    {
                      "leftValue": "={{ $('Trigger').item.json.message.hasOwnProperty('photo') }}",
                      "operator": {
                        "operation": "true",
                        "singleValue": true,
                        "type": "boolean"
                      },
                      "rightValue": ""
                    }
                  ],
                  "options": {
                    "caseSensitive": true,
                    "leftValue": "",
                    "typeValidation": "strict"
                  }
                },
                "outputKey": "YOUR_CREDENTIAL_HERE",
                "renameOutput": true
              },
              {
                "conditions": {
                  "combinator": "and",
                  "conditions": [
                    {
                      "id": "eb5a5507-4374-46c9-b8eb-25b36cbe17ee",
                      "leftValue": "={{ $('Trigger').item.json.message.hasOwnProperty('document') }}",
                      "operator": {
                        "operation": "true",
                        "singleValue": true,
                        "type": "boolean"
                      },
                      "rightValue": "2"
                    }
                  ],
                  "options": {
                    "caseSensitive": true,
                    "leftValue": "",
                    "typeValidation": "strict"
                  }
                },
                "outputKey": "YOUR_CREDENTIAL_HERE",
                "renameOutput": true
              },
              {
                "conditions": {
                  "combinator": "and",
                  "conditions": [
                    {
                      "id": "b5a43050-e657-4b56-aa9b-290a94aa8902",
                      "leftValue": "={{ $('Trigger').item.json.message.hasOwnProperty('voice') }}",
                      "operator": {
                        "operation": "true",
                        "singleValue": true,
                        "type": "boolean"
                      },
                      "rightValue": ""
                    }
                  ],
                  "options": {
                    "caseSensitive": true,
                    "leftValue": "",
                    "typeValidation": "strict"
                  }
                },
                "outputKey": "YOUR_CREDENTIAL_HERE",
                "renameOutput": true
              }
            ]
          }
        },
        "type": "n8n-nodes-base.switch",
        "typeVersion": 3
      },
      {
        "credentials": {
          "telegramApi": {
            "id": "REDACTED"
          }
        },
        "name": "Telegram1",
        "parameters": {
          "additionalFields": {
            "appendAttribution": false
          },
          "chatId": "={{ $('Trigger').item.json.message.from.id }}",
          "text": "Photo"
        },
        "type": "n8n-nodes-base.telegram",
        "typeVersion": 1.2
      },
      {
        "credentials": {
          "telegramApi": {
            "id": "REDACTED"
          }
        },
        "name": "Telegram2",
        "parameters": {
          "additionalFields": {
            "appendAttribution": false
          },
          "chatId": "={{ $('Trigger').item.json.message.from.id }}",
          "text": "File"
        },
        "type": "n8n-nodes-base.telegram",
        "typeVersion": 1.2
      },
      {
        "credentials": {
          "telegramApi": {
            "id": "REDACTED"
          }
        },
        "name": "Telegram3",
        "parameters": {
          "additionalFields": {
            "appendAttribution": false
          },
          "chatId": "={{ $('Trigger').item.json.callback_query.data }}",
          "text": "Callback"
        },
        "type": "n8n-nodes-base.telegram",
        "typeVersion": 1.2
      },
      {
        "credentials": {
          "telegramApi": {
            "id": "REDACTED"
          }
        },
        "name": "Telegram4",
        "parameters": {
          "additionalFields": {
            "appendAttribution": false
          },
          "chatId": "={{ $('Trigger').item.json.message.from.id }}",
          "text": "Text"
        },
        "type": "n8n-nodes-base.telegram",
        "typeVersion": 1.2
      },
      {
        "credentials": {
          "telegramApi": {
            "id": "REDACTED"
          }
        },
        "name": "Telegram5",
        "parameters": {
          "additionalFields": {
            "appendAttribution": false
          },
          "chatId": "={{ $('Trigger').item.json.message.from.id }}",
          "text": "Voice"
        },
        "type": "n8n-nodes-base.telegram",
        "typeVersion": 1.2
      },
      {
        "credentials": {
          "telegramApi": {
            "id": "REDACTED"
          }
        },
        "name": "Telegram6",
        "parameters": {
          "additionalFields": {
            "appendAttribution": false
          },
          "chatId": "={{ $('Trigger').item.json.message.from.id }}",
          "text": "Don't know the command"
        },
        "type": "n8n-nodes-base.telegram",
        "typeVersion": 1.2
      },
      {
        "credentials": {
          "telegramApi": {
            "id": "REDACTED"
          }
        },
        "name": "Trigger",
        "parameters": {
          "additionalFields": {},
          "updates": [
            "*"
          ]
        },
        "type": "n8n-nodes-base.telegramTrigger",
        "typeVersion": 1.1
      },
      {
        "name": "Trigger Data for Payment",
        "parameters": {
          "jsonOutput": "={{ Object.assign({}, $('Trigger').item.json, { \"action\": \"HandlePayment\" }) }}",
          "mode": "raw",
          "options": {}
        },
        "type": "n8n-nodes-base.set",
        "typeVersion": 3.4
      },
      {
        "name": "Trigger Data for Register",
        "parameters": {
          "jsonOutput": "={{ $('Trigger').item.json }}",
          "mode": "raw",
          "options": {}
        },
        "type": "n8n-nodes-base.set",
        "typeVersion": 3.4
      }
    ]
  },
  "nodeCount": 30,
  "integrationCount": 2,
  "difficulty": "Advanced",
  "estimatedSetupTime": "45 Mins",
  "integrations": [
    "Telegram",
    "Google Sheets"
  ],
  "securityStatus": "Passed",
  "verified": true,
  "featured": true,
  "downloadCount": 156,
  "viewCount": 711,
  "workflowOrigin": "third_party_import",
  "instructionStatus": "auto_generated",
  "instructions": {
    "prerequisites": [
      "An active n8n instance installed locally, in a Docker container, or hosted on n8n Cloud.",
      "Basic familiarity with importing JSON templates in n8n."
    ],
    "setupInstructions": [
      "Download the JSON configuration for this workflow.",
      "Import the JSON into n8n.",
      "Ensure you set up credentials for all connected integrations.",
      "Test your trigger and run execution."
    ],
    "requiredAccounts": [
      "Telegram Account",
      "Google Sheets Account"
    ],
    "requiredCredentials": [
      "telegram  A P I details",
      "google Sheets  O Auth2  A P I details"
    ],
    "configurationSteps": [
      "Verify the settings of the trigger node \"Trigger\".",
      "Open the \"Telegram1\" node (n8n-nodes-base.telegram) and configure the action parameters, mappings, and fields.",
      "Open the \"Telegram2\" node (n8n-nodes-base.telegram) and configure the action parameters, mappings, and fields.",
      "Open the \"Telegram3\" node (n8n-nodes-base.telegram) and configure the action parameters, mappings, and fields.",
      "Open the \"Telegram4\" node (n8n-nodes-base.telegram) and configure the action parameters, mappings, and fields.",
      "Open the \"Sticky Note\" node (n8n-nodes-base.stickyNote) and configure the action parameters, mappings, and fields.",
      "Open the \"Sticky Note1\" node (n8n-nodes-base.stickyNote) and configure the action parameters, mappings, and fields.",
      "Open the \"Sticky Note2\" node (n8n-nodes-base.stickyNote) and configure the action parameters, mappings, and fields.",
      "Open the \"Sticky Note3\" node (n8n-nodes-base.stickyNote) and configure the action parameters, mappings, and fields.",
      "Open the \"Sticky Note4\" node (n8n-nodes-base.stickyNote) and configure the action parameters, mappings, and fields.",
      "Open the \"Telegram5\" node (n8n-nodes-base.telegram) and configure the action parameters, mappings, and fields.",
      "Open the \"Switch_MessageType\" node (n8n-nodes-base.switch) and configure the action parameters, mappings, and fields.",
      "Open the \"Sticky Note5\" node (n8n-nodes-base.stickyNote) and configure the action parameters, mappings, and fields.",
      "Open the \"Telegram6\" node (n8n-nodes-base.telegram) and configure the action parameters, mappings, and fields.",
      "Open the \"Menu\" node (n8n-nodes-base.switch) and configure the action parameters, mappings, and fields.",
      "Open the \"Command?\" node (n8n-nodes-base.if) and configure the action parameters, mappings, and fields.",
      "Open the \"Change status\" Google Sheets node.",
      "Ensure you select the spreadsheet file and specific tab/sheet from the dropdown menus.",
      "Map the input JSON keys to your target sheet columns.",
      "Open the \"Start bot?\" node (n8n-nodes-base.if) and configure the action parameters, mappings, and fields.",
      "Open the \"Register\" node (n8n-nodes-base.executeWorkflow) and configure the action parameters, mappings, and fields.",
      "Open the \"Payment Handler\" node (n8n-nodes-base.executeWorkflow) and configure the action parameters, mappings, and fields.",
      "Open the \"Switch\" node (n8n-nodes-base.switch) and configure the action parameters, mappings, and fields.",
      "Open the \"Send Invoice\" node (n8n-nodes-base.executeWorkflow) and configure the action parameters, mappings, and fields.",
      "Open the \"Sticky Note6\" node (n8n-nodes-base.stickyNote) and configure the action parameters, mappings, and fields.",
      "Open the \"Sticky Note7\" node (n8n-nodes-base.stickyNote) and configure the action parameters, mappings, and fields.",
      "Open the \"Switch_Commands\" node (n8n-nodes-base.switch) and configure the action parameters, mappings, and fields.",
      "Open the \"Error Handler\" node (n8n-nodes-base.stopAndError) and configure the action parameters, mappings, and fields.",
      "Locate the Set/Edit fields node \"Global data\".",
      "Define or edit values for variables that are referenced in downstream nodes.",
      "Locate the Set/Edit fields node \"Trigger Data for Payment\".",
      "Define or edit values for variables that are referenced in downstream nodes.",
      "Locate the Set/Edit fields node \"Trigger Data for Register\".",
      "Define or edit values for variables that are referenced in downstream nodes.",
      "Locate the Set/Edit fields node \"Data for Invoice\".",
      "Define or edit values for variables that are referenced in downstream nodes."
    ],
    "testingSteps": [
      "Click the \"Test step\" or \"Listen for test event\" button on your Trigger node.",
      "Send a test trigger from your source service (e.g. fill a test form or trigger a webhook trigger).",
      "Verify that the node canvas lights up green, indicating successful data flow.",
      "Open the final destination node to confirm that output records were saved correctly."
    ],
    "expectedResult": "Upon trigger activation, inputs will flow through the configured nodes and execute actions successfully.",
    "troubleshooting": [
      "Check credential warning symbols. Most workflow issues stem from expired OAuth connections or missing API permissions.",
      "Verify that the data keys coming from your Trigger node match the exact names mapped in subsequent nodes (e.g., {{ $json.body.email }}).",
      "Open the Execution history tab in n8n to view logs and determine which node failed."
    ],
    "securityNotes": [
      "Never hardcode API keys, passwords, or authentication bearer tokens in the plain text fields of node parameters.",
      "If you download or share this workflow JSON, sanitize any sensitive parameters or configuration nodes."
    ],
    "customizationIdeas": [
      "Add an email node at the end to notify you of successful executions.",
      "Incorporate an AI LLM node to summarize trigger payloads before writing them to integrations."
    ]
  },
  "qualityScore": 100,
  "validationStatus": "Valid",
  "provenanceStatus": "source_repository_indexed",
  "importBatch": "zie619-source-2026-07",
  "sources": [
    {
      "id": "src-vltqm6ywb",
      "workflowId": "telegramtrigger-workflow-urmuz",
      "sourceName": "Zie619 n8n Workflows Repository",
      "sourceUrl": "https://github.com/Zie619/n8n-workflows/blob/main/workflows/Executeworkflow/0569_Executeworkflow_Telegram_Update_Triggered.json",
      "sourceAuthor": "Original author not identified",
      "sourceLicense": "MIT License",
      "sourceRepository": "https://github.com/Zie619/n8n-workflows",
      "sourceFilePath": "Executeworkflow\\0569_Executeworkflow_Telegram_Update_Triggered.json",
      "discoveredAt": "2026-07-15T11:18:21.930Z"
    }
  ],
  "createdAt": "2026-07-15T11:18:21.930Z",
  "updatedAt": "2026-07-15T11:18:21.930Z"
}